plateaukit/__init__.py
plateaukit/__main__.py
plateaukit/cli/__init__.py
plateaukit/cli/base.py
plateaukit/cli/cli.py
plateaukit/cli/commands/__init__.py
plateaukit/cli/commands/config.py
plateaukit/cli/commands/export.py
plateaukit/cli/commands/info.py
plateaukit/cli/commands/install.py
plateaukit/cli/commands/prebuild.py
plateaukit/config.py
plateaukit/constants.py
plateaukit/core/__init__.py
plateaukit/core/area/__init__.py
plateaukit/core/area/_export.py
plateaukit/core/area/_llm.py
plateaukit/core/dataset/__init__.py
plateaukit/core/dataset/_area.py
plateaukit/core/dataset/_dataset.py
plateaukit/core/dataset/_to_cityjson.py
plateaukit/core/dataset/_to_geojson.py
plateaukit/core/layer.py
plateaukit/core/models/__init__.py
plateaukit/core/models/building.py
plateaukit/core/widgets/cityview_widget.py
plateaukit/core/widgets/interactive_deck.py
plateaukit/defaults.py
plateaukit/download/__init__.py
plateaukit/download/downloader.py
plateaukit/download/list.py
plateaukit/exporters/__init__.py
plateaukit/exporters/cityjson/vertices_map.py
plateaukit/exporters/cityjson/writer.py
plateaukit/exporters/geojson/__init__.py
plateaukit/exporters/geojson/_parallel.py
plateaukit/exporters/geojson/_serial.py
plateaukit/exporters/geojson/_single.py
plateaukit/exporters/geojson2/__init__.py
plateaukit/exporters/geojson2/writer.py
plateaukit/exporters/parallel_writer.py
plateaukit/exporters/quantized_mesh.py
plateaukit/geocoding.py
plateaukit/installer.py
plateaukit/logger.py
plateaukit/parallel.py
plateaukit/prebuild/__init__.py
plateaukit/prebuild/_cityobjectsdb.py
plateaukit/prebuild/_dem.py
plateaukit/readers/citygml/__init__.py
plateaukit/readers/citygml/citygml_dataset.py
plateaukit/readers/citygml/constants.py
plateaukit/readers/citygml/extractors/__init__.py
plateaukit/readers/citygml/extractors/city_object_extractors.py
plateaukit/readers/citygml/ir_models.py
plateaukit/readers/citygml/parsers/__init__.py
plateaukit/readers/citygml/parsers/city_gml_parser.py
plateaukit-0.18.2.dist-info/LICENSE.txt
plateaukit-0.18.2.dist-info/METADATA
plateaukit-0.18.2.dist-info/WHEEL
plateaukit-0.18.2.dist-info/entry_points.txt
plateaukit-0.18.2.dist-info/RECORD
