Metadata-Version: 2.3
Name: plateaukit
Version: 0.18.2
Summary: Python library and utility for 3D city models by MLIT Project PLATEAU
License: MIT
Author: Kentaro Ozeki
Author-email: 32771324+ozekik@users.noreply.github.com
Requires-Python: >=3.10,<4.0
Classifier: License :: OSI Approved :: MIT License
Classifier: Programming Language :: Python :: 3
Classifier: Programming Language :: Python :: 3.10
Classifier: Programming Language :: Python :: 3.11
Classifier: Programming Language :: Python :: 3.12
Classifier: Programming Language :: Python :: 3.13
Provides-Extra: all
Provides-Extra: citygml
Provides-Extra: llm
Provides-Extra: quantized-mesh
Requires-Dist: bidict (>=0.22.1,<0.24)
Requires-Dist: cityview (>=0.1.0,<1)
Requires-Dist: click (>=8.1.3,<9.0.0)
Requires-Dist: fast-simplification (>=0.1.7,<0.2.0) ; extra == "quantized-mesh"
Requires-Dist: flatgeobuf (>=0.3.0,<0.4.0)
Requires-Dist: fs (>=2.4.16,<3.0.0)
Requires-Dist: geojson (>=3.1.0,<4.0.0)
Requires-Dist: geopandas (>=1.0.0,<2.0.0)
Requires-Dist: ipydeck (>=0.4.3,<0.5.0)
Requires-Dist: ipython (>=7.34.0,<9)
Requires-Dist: ipywidgets (>=8.1.2,<9.0.0)
Requires-Dist: langchain (>=0.3.21,<0.4.0) ; extra == "llm"
Requires-Dist: langchain_experimental (>=0.3.4,<0.4.0) ; extra == "llm"
Requires-Dist: loguru (>=0.6.0,<0.8)
Requires-Dist: lxml (>=5.0.0,<6.0.0)
Requires-Dist: normalize-japanese-addresses (>=0.0.9,<0.0.10)
Requires-Dist: numpy (>=1.26.0,<3)
Requires-Dist: platformdirs (>=4.0.0,<5.0.0)
Requires-Dist: prettytable (>=3.6.0,<4.0.0)
Requires-Dist: pyarrow (>=17.0.0) ; sys_platform != "emscripten"
Requires-Dist: pydantic (>=1,<3)
Requires-Dist: pydeck (>=0.8.0,<0.10)
Requires-Dist: pyodide-http (>=0.2.1,<0.3.0) ; sys_platform == "emscripten"
Requires-Dist: pyogrio (>=0.7.2,<1) ; (sys_platform != "emscripten") and (extra == "all" or extra == "citygml")
Requires-Dist: pyproj (>=3.4.1,<4.0.0)
Requires-Dist: quantized-mesh-encoder (>=0.4.3,<0.5.0) ; extra == "quantized-mesh"
Requires-Dist: requests (>=2.28.2,<3.0.0)
Requires-Dist: rich[jupyter] (>=13.7.0,<14.0.0)
Project-URL: Homepage, https://ozekik.github.io/plateaukit/
Project-URL: Repository, https://github.com/ozekik/plateaukit
